tool_calling_llm/__init__.py
tool_calling_llm/tool_calling_llm.py
tool_calling_llm-0.1.2.dist-info/LICENSE
tool_calling_llm-0.1.2.dist-info/METADATA
tool_calling_llm-0.1.2.dist-info/WHEEL
tool_calling_llm-0.1.2.dist-info/RECORD
