Metadata-Version: 2.1
Name: tool_calling_llm
Version: 0.1.2
Summary: Convert any LangChain Chat Model into a Tool Calling LLM
Author: Karim Lalani
Author-email: jimmy00784@gmail.com
Requires-Python: >=3.9,<4.0
Classifier: License :: OSI Approved :: MIT License
Classifier: Operating System :: OS Independent
Classifier: Programming Language :: Python :: 3
Classifier: Programming Language :: Python :: 3.9
Classifier: Programming Language :: Python :: 3.10
Classifier: Programming Language :: Python :: 3.11
Classifier: Programming Language :: Python :: 3.12
Requires-Dist: langchain (>=0.3,<0.4)
Project-URL: Homepage, https://github.com/lalanikarim/tool_calling_llm
Project-URL: Issues, https://github.com/lalanikarim/tool_calling_llm/issues
